af_org_model_manager/__init__.py
af_org_model_manager/api_client.py
af_org_model_manager/configuration.py
af_org_model_manager/rest.py
af_org_model_manager/api/__init__.py
af_org_model_manager/api/arista_flow_service_api.py
af_org_model_manager/api/client_administration_api.py
af_org_model_manager/api/default_api.py
af_org_model_manager/api/enity_remote_iterator_api.py
af_org_model_manager/api/global_security_manager_api.py
af_org_model_manager/api/model_explorer_api.py
af_org_model_manager/api/org_model_manager_api.py
af_org_model_manager/api/policy_resolution_api.py
af_org_model_manager/api/qa_remote_iterator_api.py
af_org_model_manager/api/ra_remote_iterator_api.py
af_org_model_manager/models/__init__.py
af_org_model_manager/models/abort_service_exception.py
af_org_model_manager/models/abort_transaction_exception.py
af_org_model_manager/models/agent_unknown_exception.py
af_org_model_manager/models/attribute_meta_data.py
af_org_model_manager/models/auth_data_app_name.py
af_org_model_manager/models/auth_data_arbitrary.py
af_org_model_manager/models/auth_data_org_pos.py
af_org_model_manager/models/auth_data_org_pos_list.py
af_org_model_manager/models/auth_data_password.py
af_org_model_manager/models/auth_data_user_name.py
af_org_model_manager/models/auth_data_user_session_id.py
af_org_model_manager/models/authentication_data.py
af_org_model_manager/models/authentication_exception.py
af_org_model_manager/models/body.py
af_org_model_manager/models/body1.py
af_org_model_manager/models/body10.py
af_org_model_manager/models/body2.py
af_org_model_manager/models/body3.py
af_org_model_manager/models/body4.py
af_org_model_manager/models/body5.py
af_org_model_manager/models/body6.py
af_org_model_manager/models/body7.py
af_org_model_manager/models/body8.py
af_org_model_manager/models/body9.py
af_org_model_manager/models/boolean_comparison.py
af_org_model_manager/models/client_session_details.py
af_org_model_manager/models/combining_filter.py
af_org_model_manager-3.0.3.dist-info/LICENSE
af_org_model_manager-3.0.3.dist-info/METADATA
af_org_model_manager-3.0.3.dist-info/WHEEL
af_org_model_manager-3.0.3.dist-info/top_level.txt
af_org_model_manager-3.0.3.dist-info/RECORD
